<?xml version="1.0" encoding="UTF-8"?>
<objects serializationModel="Studio.02.02.00">
	<object class="AudioFile" id="{50c75841-1c60-4690-8475-58c4698c4c58}">
		<property name="assetPath">
			<value>ptuce/pizzatime/Pizza_Tower_-_Absolute_AbsurZiti_Lap_4_Fanmade_OST.wav</value>
		</property>
		<property name="isStreaming">
			<value>true</value>
		</property>
		<property name="frequencyInKHz">
			<value>48</value>
		</property>
		<property name="channelCount">
			<value>2</value>
		</property>
		<property name="length">
			<value>137.07902083333335</value>
		</property>
		<relationship name="masterAssetFolder">
			<destination>{bf575252-09c1-4fff-a9f7-5be08d17b6ed}</destination>
		</relationship>
	</object>
</objects>
